autora/experimentalist/sampler/uncertainty_sampler/__init__.py
Autora_Experimentalist_Sampler_Uncertainty_Sampler-1.0.0rc0.dist-info/METADATA
Autora_Experimentalist_Sampler_Uncertainty_Sampler-1.0.0rc0.dist-info/WHEEL
Autora_Experimentalist_Sampler_Uncertainty_Sampler-1.0.0rc0.dist-info/top_level.txt
Autora_Experimentalist_Sampler_Uncertainty_Sampler-1.0.0rc0.dist-info/RECORD
