Metadata-Version: 2.1
Name: Autora-Experimentalist-Sampler-Uncertainty-Sampler
Version: 1.0.0rc0
Summary: Sampler based on where the model is least certain.
Author-email: "Built by Sebastian Musslick, refactored by Chad Williams" <sebastian_musslick@brown.edu>
License: MIT license
Project-URL: homepage, http://www.empiricalresearch.ai
Project-URL: repository, https://github.com/AutoResearch/autora-experimentalist-sampler-uncertainty-sampler
Project-URL: documentation, https://autoresearch.github.io/autora/
Requires-Python: <4,>=3.8
Requires-Dist: autora-core
Requires-Dist: scikit-learn
Provides-Extra: dev
Requires-Dist: autora-core[dev] ; extra == 'dev'
